rsfsup/__init__.py
rsfsup/common.py
rsfsup/fsup.py
rsfsup/mass_memory.py
rsfsup/status.py
rsfsup/version.py
rsfsup/spectrum_analyzer/__init__.py
rsfsup/spectrum_analyzer/amplitude.py
rsfsup/spectrum_analyzer/bandwidth.py
rsfsup/spectrum_analyzer/display.py
rsfsup/spectrum_analyzer/frequency.py
rsfsup/spectrum_analyzer/instrument.py
rsfsup/spectrum_analyzer/markers.py
rsfsup/spectrum_analyzer/sweep.py
rsfsup/spectrum_analyzer/traces.py
rsfsup/spectrum_analyzer/trigger.py
rsfsup/ssa/__init__.py
rsfsup/ssa/configure.py
rsfsup/ssa/display.py
rsfsup/ssa/instrument.py
rsfsup/ssa/traces.py
rsfsup-0.1.21.dist-info/LICENSE
rsfsup-0.1.21.dist-info/METADATA
rsfsup-0.1.21.dist-info/WHEEL
rsfsup-0.1.21.dist-info/top_level.txt
rsfsup-0.1.21.dist-info/RECORD
