Metadata-Version: 2.1
Name: rsfsup
Version: 0.1.21
Summary: Communication with Rohde&Schwarz FSUP Signal Source Analyzer
Home-page: https://github.com/l-johnston/rsfsup
Author: Lee Johnston
Author-email: lee.johnston.100@gmail.com
License: MIT
Platform: UNKNOWN
Classifier: Programming Language :: Python :: 3
Classifier: Topic :: Scientific/Engineering
Classifier: License :: OSI Approved :: MIT License
Classifier: Intended Audience :: Science/Research
Requires-Dist: pyvisa
Requires-Dist: matplotlib
Requires-Dist: unyt
